metacompose
