Metadata-Version: 1.0
Name: meta-compose
Version: 0.1.3
Summary: Templating wrapper for docker-compose
Home-page: https://github.com/webcrofting/meta-compose
Author: Christoph Witzany
Author-email: UNKNOWN
License: Apache License 2.0
Platform: UNKNOWN
